ben_python_utils/__init__.py
ben_python_utils/df_process.py
ben_python_utils/file_process.py
ben_python_utils-1.0.0.dist-info/LICENSE.txt
ben_python_utils-1.0.0.dist-info/METADATA
ben_python_utils-1.0.0.dist-info/WHEEL
ben_python_utils-1.0.0.dist-info/top_level.txt
ben_python_utils-1.0.0.dist-info/RECORD
