Metadata-Version: 2.1
Name: ben-python-utils
Version: 1.0.0
Summary: Some utilities for data analysis with python
Home-page: https://github.com/hjben/python-utils
Author: hjben
Author-email: hj.ben.kim@gmail.com
License: MIT
Platform: UNKNOWN
Classifier: Programming Language :: Python :: 3
Classifier: License :: OSI Approved :: MIT License
Classifier: Operating System :: OS Independent
Classifier: Natural Language :: English
Requires-Dist: pandas
